[
  {
    "id": "topic1",
    "title": "Chủ đề 1: Bí Mật Ngôi Nhà",
    "icon": "🏠",
    "lessons": [
      {
        "id": "lesson1-1",
        "title": "Bài 1: Living Room",
        "path": "/data/lessons/lesson1-1.json"
      },
      {
        "id": "lesson1-2",
        "title": "Bài 2: Kitchen",
        "path": "/data/lessons/lesson1-2.json"
      },
      {
        "id": "lesson1-3",
        "title": "Bài 3: Bedroom",
        "path": "/data/lessons/lesson1-3.json"
      },
      {
        "id": "lesson1-4",
        "title": "Bài 4: Bathroom",
        "path": "/data/lessons/lesson1-4.json"
      },
       {
        "id": "lesson1-5",
        "title": "Bài 5: Dining room",
        "path": "/data/lessons/lesson1-5.json"
      },
        {
        "id": "lesson1-6",
        "title": "Bài 6: Laundry Room",
        "path": "/data/lessons/lesson1-6.json"
      }
      
    ]
  },
  {
    "id": "topic2",
    "title": "Ngữ Pháp",
    "icon": "🌳",
    "lessons": [
      {
        "id": "lesson2-1",
        "title": "Bài 1: Mạo từ a, an, the",
        "path": "/data/lessons/lesson2-1.json"
      }
    ]
  },
   {
    "id": "topic3",
    "title": "Chủ đề 3: Thế giới động vật",
    "icon": "🐱",
    "lessons": [
      {
        "id": "lesson3-1",
        "title": "Bài 1: Các loại trái cây",
        "path": "/data/lessons/lesson3-1.json"
      }
    ]
  }
]